[
    {
        "%vlocity_namespace%__DomainObjectAPIName__c": "OrderItem",
        "%vlocity_namespace%__DomainObjectCreationOrder__c": 1,
        "%vlocity_namespace%__DomainObjectFieldAPIName__c": "%vlocity_namespace%__Action__c",
        "%vlocity_namespace%__GlobalKey__c": "e28cfac2-af75-54cb-5395-5927b7c59a54",
        "%vlocity_namespace%__InterfaceFieldAPIName__c": "action",
        "%vlocity_namespace%__IsDisabled__c": false,
        "%vlocity_namespace%__IsRequiredForUpsert__c": false,
        "%vlocity_namespace%__MapId__c": "INWIB2C_updateOrderInformation36324714284142967",
        "%vlocity_namespace%__OMplusSyncEnabled__c": true,
        "%vlocity_namespace%__UpsertKey__c": false,
        "CurrencyIsoCode": "MAD",
        "Name": "INWIB2C_updateOrderInformation",
        "VlocityDataPackType": "SObject",
        "VlocityRecordSObjectType": "%vlocity_namespace%__DRMapItem__c"
    },
    {
        "%vlocity_namespace%__DomainObjectAPIName__c": "OrderItem",
        "%vlocity_namespace%__DomainObjectCreationOrder__c": 1,
        "%vlocity_namespace%__DomainObjectFieldAPIName__c": "@INWIB2C_ATT_RT_MSISDN",
        "%vlocity_namespace%__GlobalKey__c": "91865641-58ea-6b3c-e56c-a32f7bcd8c22",
        "%vlocity_namespace%__InterfaceFieldAPIName__c": "portedMDN",
        "%vlocity_namespace%__IsDisabled__c": false,
        "%vlocity_namespace%__IsRequiredForUpsert__c": false,
        "%vlocity_namespace%__MapId__c": "INWIB2C_updateOrderInformation8134658297184609",
        "%vlocity_namespace%__OMplusSyncEnabled__c": true,
        "%vlocity_namespace%__UpsertKey__c": false,
        "CurrencyIsoCode": "MAD",
        "Name": "INWIB2C_updateOrderInformation",
        "VlocityDataPackType": "SObject",
        "VlocityRecordSObjectType": "%vlocity_namespace%__DRMapItem__c"
    },
    {
        "%vlocity_namespace%__DomainObjectAPIName__c": "OrderItem",
        "%vlocity_namespace%__DomainObjectCreationOrder__c": 1,
        "%vlocity_namespace%__DomainObjectFieldAPIName__c": "Id",
        "%vlocity_namespace%__GlobalKey__c": "a2e85b8c-ccec-16bd-85ba-60d8e9a00415",
        "%vlocity_namespace%__InterfaceFieldAPIName__c": "OIId",
        "%vlocity_namespace%__IsDisabled__c": false,
        "%vlocity_namespace%__IsRequiredForUpsert__c": false,
        "%vlocity_namespace%__MapId__c": "INWIB2C_updateOrderInformation9773986893487927",
        "%vlocity_namespace%__OMplusSyncEnabled__c": true,
        "%vlocity_namespace%__UpsertKey__c": true,
        "CurrencyIsoCode": "MAD",
        "Name": "INWIB2C_updateOrderInformation",
        "VlocityDataPackType": "SObject",
        "VlocityRecordSObjectType": "%vlocity_namespace%__DRMapItem__c"
    },
    {
        "%vlocity_namespace%__ConfigurationValue__c": "FAKEMAPPING",
        "%vlocity_namespace%__DomainObjectAPIName__c": "OrderItem",
        "%vlocity_namespace%__DomainObjectCreationOrder__c": 1,
        "%vlocity_namespace%__DomainObjectFieldAPIName__c": "Id",
        "%vlocity_namespace%__FilterOperator__c": "=",
        "%vlocity_namespace%__GlobalKey__c": "05fa7fde-2bf9-3a97-2b0c-4ceeb8d02e42",
        "%vlocity_namespace%__IsDisabled__c": true,
        "%vlocity_namespace%__IsRequiredForUpsert__c": false,
        "%vlocity_namespace%__MapId__c": "INWIB2C_updateOrderInformation7689010615422136",
        "%vlocity_namespace%__OMplusSyncEnabled__c": true,
        "%vlocity_namespace%__UpsertKey__c": false,
        "CurrencyIsoCode": "MAD",
        "Name": "INWIB2C_updateOrderInformation",
        "VlocityDataPackType": "SObject",
        "VlocityRecordSObjectType": "%vlocity_namespace%__DRMapItem__c"
    }
]