[
    {
        "%vlocity_namespace%__DomainObjectAPIName__c": "json",
        "%vlocity_namespace%__DomainObjectCreationOrder__c": 0,
        "%vlocity_namespace%__DomainObjectFieldAPIName__c": "FRL",
        "%vlocity_namespace%__FilterGroup__c": 0,
        "%vlocity_namespace%__FilterOperator__c": "=",
        "%vlocity_namespace%__FilterValue__c": "FRLId",
        "%vlocity_namespace%__GlobalKey__c": "25ab5231-167b-bf48-3610-1cd5a2698164",
        "%vlocity_namespace%__InterfaceFieldAPIName__c": "Id",
        "%vlocity_namespace%__InterfaceObjectLookupOrder__c": 1,
        "%vlocity_namespace%__InterfaceObjectName__c": "%vlocity_namespace%__FulfilmentRequestLine__c",
        "%vlocity_namespace%__IsDisabled__c": false,
        "%vlocity_namespace%__IsRequiredForUpsert__c": false,
        "%vlocity_namespace%__MapId__c": "INWIB2C-DRE-GetFRL_OSS_Migration_PrepCustom8739",
        "%vlocity_namespace%__OMplusSyncEnabled__c": true,
        "%vlocity_namespace%__UpsertKey__c": false,
        "CurrencyIsoCode": "MAD",
        "Name": "INWIB2C-DRE-GetFRL_OSS_Migration_Prep",
        "VlocityDataPackType": "SObject",
        "VlocityRecordSObjectType": "%vlocity_namespace%__DRMapItem__c"
    },
    {
        "%vlocity_namespace%__DomainObjectAPIName__c": "json",
        "%vlocity_namespace%__DomainObjectCreationOrder__c": 0,
        "%vlocity_namespace%__DomainObjectFieldAPIName__c": "FRL:ChildFRL",
        "%vlocity_namespace%__FilterGroup__c": 0,
        "%vlocity_namespace%__FilterOperator__c": "<>",
        "%vlocity_namespace%__FilterValue__c": "\"NoChange\"",
        "%vlocity_namespace%__GlobalKey__c": "2ff4a36d-c08a-7f73-6317-f476787dd65f",
        "%vlocity_namespace%__InterfaceFieldAPIName__c": "%vlocity_namespace%__Action__c",
        "%vlocity_namespace%__InterfaceObjectLookupOrder__c": 2,
        "%vlocity_namespace%__InterfaceObjectName__c": "%vlocity_namespace%__FulfilmentRequestLine__c",
        "%vlocity_namespace%__IsDisabled__c": false,
        "%vlocity_namespace%__IsRequiredForUpsert__c": false,
        "%vlocity_namespace%__MapId__c": "INWIB2C-DRE-GetFRL_OSS_Migration_PrepCustom5710",
        "%vlocity_namespace%__OMplusSyncEnabled__c": true,
        "%vlocity_namespace%__UpsertKey__c": false,
        "CurrencyIsoCode": "MAD",
        "Name": "INWIB2C-DRE-GetFRL_OSS_Migration_Prep",
        "VlocityDataPackType": "SObject",
        "VlocityRecordSObjectType": "%vlocity_namespace%__DRMapItem__c"
    },
    {
        "%vlocity_namespace%__DomainObjectAPIName__c": "json",
        "%vlocity_namespace%__DomainObjectCreationOrder__c": 0,
        "%vlocity_namespace%__DomainObjectFieldAPIName__c": "FRL:ChildFRL",
        "%vlocity_namespace%__FilterGroup__c": 0,
        "%vlocity_namespace%__FilterOperator__c": "LIKE",
        "%vlocity_namespace%__FilterValue__c": "childFRLLineNumber",
        "%vlocity_namespace%__GlobalKey__c": "5b4d361e-c001-f633-5e26-3276f473daab",
        "%vlocity_namespace%__InterfaceFieldAPIName__c": "%vlocity_namespace%__LineNumber__c",
        "%vlocity_namespace%__InterfaceObjectLookupOrder__c": 2,
        "%vlocity_namespace%__InterfaceObjectName__c": "%vlocity_namespace%__FulfilmentRequestLine__c",
        "%vlocity_namespace%__IsDisabled__c": false,
        "%vlocity_namespace%__IsRequiredForUpsert__c": false,
        "%vlocity_namespace%__MapId__c": "INWIB2C-DRE-GetFRL_OSS_Migration_PrepCustom417",
        "%vlocity_namespace%__OMplusSyncEnabled__c": true,
        "%vlocity_namespace%__UpsertKey__c": false,
        "CurrencyIsoCode": "MAD",
        "Name": "INWIB2C-DRE-GetFRL_OSS_Migration_Prep",
        "VlocityDataPackType": "SObject",
        "VlocityRecordSObjectType": "%vlocity_namespace%__DRMapItem__c"
    },
    {
        "%vlocity_namespace%__DomainObjectAPIName__c": "json",
        "%vlocity_namespace%__DomainObjectCreationOrder__c": 0,
        "%vlocity_namespace%__DomainObjectFieldAPIName__c": "User",
        "%vlocity_namespace%__FilterGroup__c": 0,
        "%vlocity_namespace%__FilterOperator__c": "=",
        "%vlocity_namespace%__FilterValue__c": "\"$Vlocity.UserId\"",
        "%vlocity_namespace%__GlobalKey__c": "195871ed-08a2-d606-dff8-a3f1362bacd9",
        "%vlocity_namespace%__InterfaceFieldAPIName__c": "Id",
        "%vlocity_namespace%__InterfaceObjectLookupOrder__c": 3,
        "%vlocity_namespace%__InterfaceObjectName__c": "User",
        "%vlocity_namespace%__IsDisabled__c": false,
        "%vlocity_namespace%__IsRequiredForUpsert__c": false,
        "%vlocity_namespace%__MapId__c": "INWIB2C-DRE-GetFRL_OSS_Migration_PrepCustom9223",
        "%vlocity_namespace%__OMplusSyncEnabled__c": true,
        "%vlocity_namespace%__UpsertKey__c": false,
        "CurrencyIsoCode": "MAD",
        "Name": "INWIB2C-DRE-GetFRL_OSS_Migration_Prep",
        "VlocityDataPackType": "SObject",
        "VlocityRecordSObjectType": "%vlocity_namespace%__DRMapItem__c"
    },
    {
        "%vlocity_namespace%__DomainObjectAPIName__c": "Formula",
        "%vlocity_namespace%__DomainObjectCreationOrder__c": 0,
        "%vlocity_namespace%__DomainObjectFieldAPIName__c": "Formula",
        "%vlocity_namespace%__FormulaOrder__c": 1,
        "%vlocity_namespace%__FormulaResultPath__c": "FRL:uuid",
        "%vlocity_namespace%__Formula__c": "GENERATEGLOBALKEY()",
        "%vlocity_namespace%__GlobalKey__c": "eec26a7c-d96d-8ccf-2c01-c6b7c1ffc3ad",
        "%vlocity_namespace%__IsDisabled__c": false,
        "%vlocity_namespace%__IsRequiredForUpsert__c": false,
        "%vlocity_namespace%__MapId__c": "INWIB2C-DRE-GetFRL_OSS_Migration_PrepCustom2649",
        "%vlocity_namespace%__OMplusSyncEnabled__c": true,
        "%vlocity_namespace%__UpsertKey__c": false,
        "CurrencyIsoCode": "MAD",
        "Name": "INWIB2C-DRE-GetFRL_OSS_Migration_Prep",
        "VlocityDataPackType": "SObject",
        "VlocityRecordSObjectType": "%vlocity_namespace%__DRMapItem__c"
    },
    {
        "%vlocity_namespace%__DomainObjectAPIName__c": "Formula",
        "%vlocity_namespace%__DomainObjectCreationOrder__c": 0,
        "%vlocity_namespace%__DomainObjectFieldAPIName__c": "Formula",
        "%vlocity_namespace%__FormulaOrder__c": 10,
        "%vlocity_namespace%__FormulaResultPath__c": "FRL:ChildFRL:SERVICE_LEVEL_IN_Value",
        "%vlocity_namespace%__Formula__c": "IF(FRL:ChildFRL:%vlocity_namespace%__Product2Id__r.ProductCode='INWIB2C_RFS_VOICE' AND FRL:ChildFRL:@INWIB2C_ATT_DC_OSS_SERVICE='TRUE','ALLOWED','')",
        "%vlocity_namespace%__GlobalKey__c": "e4a72561-650c-328a-52ab-5102cd75eaca",
        "%vlocity_namespace%__IsDisabled__c": false,
        "%vlocity_namespace%__IsRequiredForUpsert__c": false,
        "%vlocity_namespace%__MapId__c": "INWIB2C-DRE-GetFRL_OSS_Migration_PrepCustom3381",
        "%vlocity_namespace%__OMplusSyncEnabled__c": true,
        "%vlocity_namespace%__UpsertKey__c": false,
        "CurrencyIsoCode": "MAD",
        "Name": "INWIB2C-DRE-GetFRL_OSS_Migration_Prep",
        "VlocityDataPackType": "SObject",
        "VlocityRecordSObjectType": "%vlocity_namespace%__DRMapItem__c"
    },
    {
        "%vlocity_namespace%__DomainObjectAPIName__c": "Formula",
        "%vlocity_namespace%__DomainObjectCreationOrder__c": 0,
        "%vlocity_namespace%__DomainObjectFieldAPIName__c": "Formula",
        "%vlocity_namespace%__FormulaOrder__c": 11,
        "%vlocity_namespace%__FormulaResultPath__c": "FRL:ChildFRL:SERVICE_LEVEL_OUT_Value",
        "%vlocity_namespace%__Formula__c": "IF(FRL:ChildFRL:%vlocity_namespace%__Product2Id__r.ProductCode='INWIB2C_RFS_VOICE' AND FRL:ChildFRL:@INWIB2C_ATT_DC_OSS_SERVICE='TRUE','SR4','')",
        "%vlocity_namespace%__GlobalKey__c": "e7880079-236a-d100-cd4d-5bba1af15fc8",
        "%vlocity_namespace%__IsDisabled__c": false,
        "%vlocity_namespace%__IsRequiredForUpsert__c": false,
        "%vlocity_namespace%__MapId__c": "INWIB2C-DRE-GetFRL_OSS_Migration_PrepCustom9968",
        "%vlocity_namespace%__OMplusSyncEnabled__c": true,
        "%vlocity_namespace%__UpsertKey__c": false,
        "CurrencyIsoCode": "MAD",
        "Name": "INWIB2C-DRE-GetFRL_OSS_Migration_Prep",
        "VlocityDataPackType": "SObject",
        "VlocityRecordSObjectType": "%vlocity_namespace%__DRMapItem__c"
    },
    {
        "%vlocity_namespace%__DomainObjectAPIName__c": "Formula",
        "%vlocity_namespace%__DomainObjectCreationOrder__c": 0,
        "%vlocity_namespace%__DomainObjectFieldAPIName__c": "Formula",
        "%vlocity_namespace%__FormulaOrder__c": 12,
        "%vlocity_namespace%__FormulaResultPath__c": "FRL:ChildFRL:SMS_IN_Value",
        "%vlocity_namespace%__Formula__c": "IF(FRL:ChildFRL:%vlocity_namespace%__Product2Id__r.ProductCode='INWIB2C_RFS_SMS' AND FRL:ChildFRL:@INWIB2C_ATT_DC_OSS_SERVICE='TRUE','BLOCKED','')",
        "%vlocity_namespace%__GlobalKey__c": "e9a0a0af-a97c-7370-6b1f-ed3eca60014b",
        "%vlocity_namespace%__IsDisabled__c": false,
        "%vlocity_namespace%__IsRequiredForUpsert__c": false,
        "%vlocity_namespace%__MapId__c": "INWIB2C-DRE-GetFRL_OSS_Migration_PrepCustom7921",
        "%vlocity_namespace%__OMplusSyncEnabled__c": true,
        "%vlocity_namespace%__UpsertKey__c": false,
        "CurrencyIsoCode": "MAD",
        "Name": "INWIB2C-DRE-GetFRL_OSS_Migration_Prep",
        "VlocityDataPackType": "SObject",
        "VlocityRecordSObjectType": "%vlocity_namespace%__DRMapItem__c"
    },
    {
        "%vlocity_namespace%__DomainObjectAPIName__c": "Formula",
        "%vlocity_namespace%__DomainObjectCreationOrder__c": 0,
        "%vlocity_namespace%__DomainObjectFieldAPIName__c": "Formula",
        "%vlocity_namespace%__FormulaOrder__c": 13,
        "%vlocity_namespace%__FormulaResultPath__c": "FRL:ChildFRL:SMS_OUT_Value",
        "%vlocity_namespace%__Formula__c": "IF(FRL:ChildFRL:%vlocity_namespace%__Product2Id__r.ProductCode='INWIB2C_RFS_SMS' AND FRL:ChildFRL:@INWIB2C_ATT_DC_OSS_SERVICE='TRUE','BLOCKED','')",
        "%vlocity_namespace%__GlobalKey__c": "4be71416-0d58-3719-ee2f-e877acbdc146",
        "%vlocity_namespace%__IsDisabled__c": false,
        "%vlocity_namespace%__IsRequiredForUpsert__c": false,
        "%vlocity_namespace%__MapId__c": "INWIB2C-DRE-GetFRL_OSS_Migration_PrepCustom6402",
        "%vlocity_namespace%__OMplusSyncEnabled__c": true,
        "%vlocity_namespace%__UpsertKey__c": false,
        "CurrencyIsoCode": "MAD",
        "Name": "INWIB2C-DRE-GetFRL_OSS_Migration_Prep",
        "VlocityDataPackType": "SObject",
        "VlocityRecordSObjectType": "%vlocity_namespace%__DRMapItem__c"
    },
    {
        "%vlocity_namespace%__DomainObjectAPIName__c": "Formula",
        "%vlocity_namespace%__DomainObjectCreationOrder__c": 0,
        "%vlocity_namespace%__DomainObjectFieldAPIName__c": "Formula",
        "%vlocity_namespace%__FormulaOrder__c": 14,
        "%vlocity_namespace%__FormulaResultPath__c": "FRL:ChildFRL:SERVICE_STATUS_Value",
        "%vlocity_namespace%__Formula__c": "IF(FRL:ChildFRL:%vlocity_namespace%__Product2Id__r.ProductCode='\tINWIB2C_RFS_DATA' AND FRL:ChildFRL:@INWIB2C_ATT_DC_OSS_SERVICE='TRUE','BLOCKED','')",
        "%vlocity_namespace%__GlobalKey__c": "2c7192a2-d632-124f-0dd3-d25772221725",
        "%vlocity_namespace%__IsDisabled__c": false,
        "%vlocity_namespace%__IsRequiredForUpsert__c": false,
        "%vlocity_namespace%__MapId__c": "INWIB2C-DRE-GetFRL_OSS_Migration_PrepCustom2929",
        "%vlocity_namespace%__OMplusSyncEnabled__c": true,
        "%vlocity_namespace%__UpsertKey__c": false,
        "CurrencyIsoCode": "MAD",
        "Name": "INWIB2C-DRE-GetFRL_OSS_Migration_Prep",
        "VlocityDataPackType": "SObject",
        "VlocityRecordSObjectType": "%vlocity_namespace%__DRMapItem__c"
    },
    {
        "%vlocity_namespace%__DomainObjectAPIName__c": "Formula",
        "%vlocity_namespace%__DomainObjectCreationOrder__c": 0,
        "%vlocity_namespace%__DomainObjectFieldAPIName__c": "Formula",
        "%vlocity_namespace%__FormulaOrder__c": 15,
        "%vlocity_namespace%__FormulaResultPath__c": "FRL:ChildFRL:CALL_TRANSFER_LEVEL_Value",
        "%vlocity_namespace%__Formula__c": "IF(FRL:ChildFRL:%vlocity_namespace%__Product2Id__r.ProductCode='INWIB2C_RFS_CALL_TRANSFER' AND FRL:ChildFRL:@INWIB2C_ATT_DC_OSS_SERVICE='TRUE','CFB,CFD,CFNRC,CFNRY,CFU','')",
        "%vlocity_namespace%__GlobalKey__c": "7a9cb817-6b0f-c868-f3f6-8b40f4f128d1",
        "%vlocity_namespace%__IsDisabled__c": false,
        "%vlocity_namespace%__IsRequiredForUpsert__c": false,
        "%vlocity_namespace%__MapId__c": "INWIB2C-DRE-GetFRL_OSS_Migration_PrepCustom8473",
        "%vlocity_namespace%__OMplusSyncEnabled__c": true,
        "%vlocity_namespace%__UpsertKey__c": false,
        "CurrencyIsoCode": "MAD",
        "Name": "INWIB2C-DRE-GetFRL_OSS_Migration_Prep",
        "VlocityDataPackType": "SObject",
        "VlocityRecordSObjectType": "%vlocity_namespace%__DRMapItem__c"
    },
    {
        "%vlocity_namespace%__DomainObjectAPIName__c": "Formula",
        "%vlocity_namespace%__DomainObjectCreationOrder__c": 0,
        "%vlocity_namespace%__DomainObjectFieldAPIName__c": "Formula",
        "%vlocity_namespace%__FormulaOrder__c": 16,
        "%vlocity_namespace%__FormulaResultPath__c": "FRL:ChildFRL:IROAM_SERVICE_LEVEL_Value",
        "%vlocity_namespace%__Formula__c": "IF(FRL:ChildFRL:%vlocity_namespace%__Product2Id__r.ProductCode='INWIB2C_RFS_ROAMING' AND FRL:ChildFRL:@INWIB2C_ATT_DC_OSS_SERVICE='TRUE','VSD','')",
        "%vlocity_namespace%__GlobalKey__c": "c8e57f28-07fa-e0bc-8eef-3fa55e7f4357",
        "%vlocity_namespace%__IsDisabled__c": false,
        "%vlocity_namespace%__IsRequiredForUpsert__c": false,
        "%vlocity_namespace%__MapId__c": "INWIB2C-DRE-GetFRL_OSS_Migration_PrepCustom5036",
        "%vlocity_namespace%__OMplusSyncEnabled__c": true,
        "%vlocity_namespace%__UpsertKey__c": false,
        "CurrencyIsoCode": "MAD",
        "Name": "INWIB2C-DRE-GetFRL_OSS_Migration_Prep",
        "VlocityDataPackType": "SObject",
        "VlocityRecordSObjectType": "%vlocity_namespace%__DRMapItem__c"
    },
    {
        "%vlocity_namespace%__DomainObjectAPIName__c": "Formula",
        "%vlocity_namespace%__DomainObjectCreationOrder__c": 0,
        "%vlocity_namespace%__DomainObjectFieldAPIName__c": "Formula",
        "%vlocity_namespace%__FormulaOrder__c": 2,
        "%vlocity_namespace%__FormulaResultPath__c": "FRL:ChildFRL:ACTION",
        "%vlocity_namespace%__Formula__c": "IF(FRL:ChildFRL:@INWIB2C_ATT_DC_OSS_SERVICE='TRUE',\n    IF(FRL:ChildFRL:%vlocity_namespace%__Action__c='Disconnect' \n        AND (FRL:ChildFRL:%vlocity_namespace%__Product2Id__r.ProductCode ='INWIB2C_RFS_VOICE' \n            OR FRL:ChildFRL:%vlocity_namespace%__Product2Id__r.ProductCode = 'INWIB2C_RFS_USSD'),'MOD',\n                IF(FRL:ChildFRL:%vlocity_namespace%__Action__c='Disconnect' \n                    AND (FRL:ChildFRL:%vlocity_namespace%__Product2Id__r.ProductCode = 'INWIB2C_RFS_CLIP' \n                        OR FRL:ChildFRL:%vlocity_namespace%__Product2Id__r.ProductCode = 'INWIB2C_RFS_CLIR'\n                        OR FRL:ChildFRL:%vlocity_namespace%__Product2Id__r.ProductCode = 'INWIB2C_RFS_CALLHOLD'\n                        OR FRL:ChildFRL:%vlocity_namespace%__Product2Id__r.ProductCode = 'INWIB2C_RFS_CAMEL'\n                        OR FRL:ChildFRL:%vlocity_namespace%__Product2Id__r.ProductCode = 'INWIB2C_RFS_CALLWAIT'\n                        OR FRL:ChildFRL:%vlocity_namespace%__Product2Id__r.ProductCode = 'INWIB2C_RFS_CALL_TRANSFER'),'ADD','DEL')),'')",
        "%vlocity_namespace%__GlobalKey__c": "60120d96-c6f4-a2e2-2c30-e180917dd4cf",
        "%vlocity_namespace%__IsDisabled__c": false,
        "%vlocity_namespace%__IsRequiredForUpsert__c": false,
        "%vlocity_namespace%__MapId__c": "INWIB2C-DRE-GetFRL_OSS_Migration_PrepCustom8908",
        "%vlocity_namespace%__OMplusSyncEnabled__c": true,
        "%vlocity_namespace%__UpsertKey__c": false,
        "CurrencyIsoCode": "MAD",
        "Name": "INWIB2C-DRE-GetFRL_OSS_Migration_Prep",
        "VlocityDataPackType": "SObject",
        "VlocityRecordSObjectType": "%vlocity_namespace%__DRMapItem__c"
    },
    {
        "%vlocity_namespace%__DomainObjectAPIName__c": "Formula",
        "%vlocity_namespace%__DomainObjectCreationOrder__c": 0,
        "%vlocity_namespace%__DomainObjectFieldAPIName__c": "Formula",
        "%vlocity_namespace%__FormulaOrder__c": 3,
        "%vlocity_namespace%__FormulaResultPath__c": "FRL:ChildFRL:SERVICE_LEVEL_IN_Code",
        "%vlocity_namespace%__Formula__c": "IF(FRL:ChildFRL:%vlocity_namespace%__Product2Id__r.ProductCode='INWIB2C_RFS_VOICE' AND FRL:ChildFRL:@INWIB2C_ATT_DC_OSS_SERVICE='TRUE','SERVICE_LEVEL_IN','')",
        "%vlocity_namespace%__GlobalKey__c": "bd11bb1d-b0f1-f997-274e-e6c8cd0fe32f",
        "%vlocity_namespace%__IsDisabled__c": false,
        "%vlocity_namespace%__IsRequiredForUpsert__c": false,
        "%vlocity_namespace%__MapId__c": "INWIB2C-DRE-GetFRL_OSS_Migration_PrepCustom340",
        "%vlocity_namespace%__OMplusSyncEnabled__c": true,
        "%vlocity_namespace%__UpsertKey__c": false,
        "CurrencyIsoCode": "MAD",
        "Name": "INWIB2C-DRE-GetFRL_OSS_Migration_Prep",
        "VlocityDataPackType": "SObject",
        "VlocityRecordSObjectType": "%vlocity_namespace%__DRMapItem__c"
    },
    {
        "%vlocity_namespace%__DomainObjectAPIName__c": "Formula",
        "%vlocity_namespace%__DomainObjectCreationOrder__c": 0,
        "%vlocity_namespace%__DomainObjectFieldAPIName__c": "Formula",
        "%vlocity_namespace%__FormulaOrder__c": 4,
        "%vlocity_namespace%__FormulaResultPath__c": "FRL:ChildFRL:SERVICE_LEVEL_OUT_Code",
        "%vlocity_namespace%__Formula__c": "IF(FRL:ChildFRL:%vlocity_namespace%__Product2Id__r.ProductCode='INWIB2C_RFS_VOICE' AND FRL:ChildFRL:@INWIB2C_ATT_DC_OSS_SERVICE='TRUE','SERVICE_LEVEL_OUT','')",
        "%vlocity_namespace%__GlobalKey__c": "0fe5e3b4-f92f-8e17-c493-4d3c4a57aa2c",
        "%vlocity_namespace%__IsDisabled__c": false,
        "%vlocity_namespace%__IsRequiredForUpsert__c": false,
        "%vlocity_namespace%__MapId__c": "INWIB2C-DRE-GetFRL_OSS_Migration_PrepCustom6557",
        "%vlocity_namespace%__OMplusSyncEnabled__c": true,
        "%vlocity_namespace%__UpsertKey__c": false,
        "CurrencyIsoCode": "MAD",
        "Name": "INWIB2C-DRE-GetFRL_OSS_Migration_Prep",
        "VlocityDataPackType": "SObject",
        "VlocityRecordSObjectType": "%vlocity_namespace%__DRMapItem__c"
    },
    {
        "%vlocity_namespace%__DomainObjectAPIName__c": "Formula",
        "%vlocity_namespace%__DomainObjectCreationOrder__c": 0,
        "%vlocity_namespace%__DomainObjectFieldAPIName__c": "Formula",
        "%vlocity_namespace%__FormulaOrder__c": 5,
        "%vlocity_namespace%__FormulaResultPath__c": "FRL:ChildFRL:SMS_IN_Code",
        "%vlocity_namespace%__Formula__c": "IF(FRL:ChildFRL:%vlocity_namespace%__Product2Id__r.ProductCode='INWIB2C_RFS_SMS' AND FRL:ChildFRL:@INWIB2C_ATT_DC_OSS_SERVICE='TRUE','SMS_IN','')",
        "%vlocity_namespace%__GlobalKey__c": "78e762b1-b67e-87ca-064c-688b85e6e830",
        "%vlocity_namespace%__IsDisabled__c": false,
        "%vlocity_namespace%__IsRequiredForUpsert__c": false,
        "%vlocity_namespace%__MapId__c": "INWIB2C-DRE-GetFRL_OSS_Migration_PrepCustom393",
        "%vlocity_namespace%__OMplusSyncEnabled__c": true,
        "%vlocity_namespace%__UpsertKey__c": false,
        "CurrencyIsoCode": "MAD",
        "Name": "INWIB2C-DRE-GetFRL_OSS_Migration_Prep",
        "VlocityDataPackType": "SObject",
        "VlocityRecordSObjectType": "%vlocity_namespace%__DRMapItem__c"
    },
    {
        "%vlocity_namespace%__DomainObjectAPIName__c": "Formula",
        "%vlocity_namespace%__DomainObjectCreationOrder__c": 0,
        "%vlocity_namespace%__DomainObjectFieldAPIName__c": "Formula",
        "%vlocity_namespace%__FormulaOrder__c": 6,
        "%vlocity_namespace%__FormulaResultPath__c": "FRL:ChildFRL:SMS_OUT_Code",
        "%vlocity_namespace%__Formula__c": "IF(FRL:ChildFRL:%vlocity_namespace%__Product2Id__r.ProductCode='INWIB2C_RFS_SMS' AND FRL:ChildFRL:@INWIB2C_ATT_DC_OSS_SERVICE='TRUE','SMS_OUT','')",
        "%vlocity_namespace%__GlobalKey__c": "eabb0a46-b0f0-11a2-74d8-54b2a9a80867",
        "%vlocity_namespace%__IsDisabled__c": false,
        "%vlocity_namespace%__IsRequiredForUpsert__c": false,
        "%vlocity_namespace%__MapId__c": "INWIB2C-DRE-GetFRL_OSS_Migration_PrepCustom7792",
        "%vlocity_namespace%__OMplusSyncEnabled__c": true,
        "%vlocity_namespace%__UpsertKey__c": false,
        "CurrencyIsoCode": "MAD",
        "Name": "INWIB2C-DRE-GetFRL_OSS_Migration_Prep",
        "VlocityDataPackType": "SObject",
        "VlocityRecordSObjectType": "%vlocity_namespace%__DRMapItem__c"
    },
    {
        "%vlocity_namespace%__DomainObjectAPIName__c": "Formula",
        "%vlocity_namespace%__DomainObjectCreationOrder__c": 0,
        "%vlocity_namespace%__DomainObjectFieldAPIName__c": "Formula",
        "%vlocity_namespace%__FormulaOrder__c": 7,
        "%vlocity_namespace%__FormulaResultPath__c": "FRL:ChildFRL:IROAM_SERVICE_LEVEL_Code",
        "%vlocity_namespace%__Formula__c": "IF(FRL:ChildFRL:%vlocity_namespace%__Product2Id__r.ProductCode='INWIB2C_RFS_ROAMING' AND FRL:ChildFRL:@INWIB2C_ATT_DC_OSS_SERVICE='TRUE','IROAM_SERVICE_LEVEL','')",
        "%vlocity_namespace%__GlobalKey__c": "13344967-1d82-816a-d769-e585e547f9d0",
        "%vlocity_namespace%__IsDisabled__c": false,
        "%vlocity_namespace%__IsRequiredForUpsert__c": false,
        "%vlocity_namespace%__MapId__c": "INWIB2C-DRE-GetFRL_OSS_Migration_PrepCustom4219",
        "%vlocity_namespace%__OMplusSyncEnabled__c": true,
        "%vlocity_namespace%__UpsertKey__c": false,
        "CurrencyIsoCode": "MAD",
        "Name": "INWIB2C-DRE-GetFRL_OSS_Migration_Prep",
        "VlocityDataPackType": "SObject",
        "VlocityRecordSObjectType": "%vlocity_namespace%__DRMapItem__c"
    },
    {
        "%vlocity_namespace%__DomainObjectAPIName__c": "Formula",
        "%vlocity_namespace%__DomainObjectCreationOrder__c": 0,
        "%vlocity_namespace%__DomainObjectFieldAPIName__c": "Formula",
        "%vlocity_namespace%__FormulaOrder__c": 8,
        "%vlocity_namespace%__FormulaResultPath__c": "FRL:ChildFRL:CALL_TRANSFER_LEVEL_Code",
        "%vlocity_namespace%__Formula__c": "IF(FRL:ChildFRL:%vlocity_namespace%__Product2Id__r.ProductCode='INWIB2C_RFS_CALL_TRANSFER' AND FRL:ChildFRL:@INWIB2C_ATT_DC_OSS_SERVICE='TRUE','CALL_TRANSFER_LEVEL','')",
        "%vlocity_namespace%__GlobalKey__c": "6a2de034-59dd-261f-7573-1b01d1169b59",
        "%vlocity_namespace%__IsDisabled__c": false,
        "%vlocity_namespace%__IsRequiredForUpsert__c": false,
        "%vlocity_namespace%__MapId__c": "INWIB2C-DRE-GetFRL_OSS_Migration_PrepCustom4911",
        "%vlocity_namespace%__OMplusSyncEnabled__c": true,
        "%vlocity_namespace%__UpsertKey__c": false,
        "CurrencyIsoCode": "MAD",
        "Name": "INWIB2C-DRE-GetFRL_OSS_Migration_Prep",
        "VlocityDataPackType": "SObject",
        "VlocityRecordSObjectType": "%vlocity_namespace%__DRMapItem__c"
    },
    {
        "%vlocity_namespace%__DomainObjectAPIName__c": "Formula",
        "%vlocity_namespace%__DomainObjectCreationOrder__c": 0,
        "%vlocity_namespace%__DomainObjectFieldAPIName__c": "Formula",
        "%vlocity_namespace%__FormulaOrder__c": 9,
        "%vlocity_namespace%__FormulaResultPath__c": "FRL:ChildFRL:SERVICE_STATUS_Code",
        "%vlocity_namespace%__Formula__c": "IF(FRL:ChildFRL:%vlocity_namespace%__Product2Id__r.ProductCode='\tINWIB2C_RFS_DATA' AND FRL:ChildFRL:@INWIB2C_ATT_DC_OSS_SERVICE='TRUE','SERVICE_STATUS','')",
        "%vlocity_namespace%__GlobalKey__c": "e46a4620-5bbc-5fc0-0496-a6ee1e2d2d58",
        "%vlocity_namespace%__IsDisabled__c": false,
        "%vlocity_namespace%__IsRequiredForUpsert__c": false,
        "%vlocity_namespace%__MapId__c": "INWIB2C-DRE-GetFRL_OSS_Migration_PrepCustom855",
        "%vlocity_namespace%__OMplusSyncEnabled__c": true,
        "%vlocity_namespace%__UpsertKey__c": false,
        "CurrencyIsoCode": "MAD",
        "Name": "INWIB2C-DRE-GetFRL_OSS_Migration_Prep",
        "VlocityDataPackType": "SObject",
        "VlocityRecordSObjectType": "%vlocity_namespace%__DRMapItem__c"
    },
    {
        "%vlocity_namespace%__DomainObjectAPIName__c": "json",
        "%vlocity_namespace%__DomainObjectCreationOrder__c": 1,
        "%vlocity_namespace%__DomainObjectFieldAPIName__c": "Id",
        "%vlocity_namespace%__GlobalKey__c": "cfba4ded-a174-b2ed-a1a1-87299ff16796",
        "%vlocity_namespace%__InterfaceFieldAPIName__c": "OIId",
        "%vlocity_namespace%__IsDisabled__c": false,
        "%vlocity_namespace%__IsRequiredForUpsert__c": false,
        "%vlocity_namespace%__MapId__c": "INWIB2C-DRE-GetFRL_OSS_Migration_PrepCustom4840",
        "%vlocity_namespace%__OMplusSyncEnabled__c": true,
        "%vlocity_namespace%__UpsertKey__c": false,
        "CurrencyIsoCode": "MAD",
        "Name": "INWIB2C-DRE-GetFRL_OSS_Migration_Prep",
        "VlocityDataPackType": "SObject",
        "VlocityRecordSObjectType": "%vlocity_namespace%__DRMapItem__c"
    },
    {
        "%vlocity_namespace%__DefaultValue__c": "MOD",
        "%vlocity_namespace%__DomainObjectAPIName__c": "json",
        "%vlocity_namespace%__DomainObjectCreationOrder__c": 1,
        "%vlocity_namespace%__DomainObjectFieldAPIName__c": "action",
        "%vlocity_namespace%__GlobalKey__c": "64ba5140-1d6a-90a0-848c-fdf133957ee4",
        "%vlocity_namespace%__IsDisabled__c": false,
        "%vlocity_namespace%__IsRequiredForUpsert__c": false,
        "%vlocity_namespace%__MapId__c": "INWIB2C-DRE-GetFRL_OSS_Migration_PrepCustom2848",
        "%vlocity_namespace%__OMplusSyncEnabled__c": true,
        "%vlocity_namespace%__UpsertKey__c": false,
        "CurrencyIsoCode": "MAD",
        "Name": "INWIB2C-DRE-GetFRL_OSS_Migration_Prep",
        "VlocityDataPackType": "SObject",
        "VlocityRecordSObjectType": "%vlocity_namespace%__DRMapItem__c"
    },
    {
        "%vlocity_namespace%__DefaultValue__c": "MGPR",
        "%vlocity_namespace%__DomainObjectAPIName__c": "json",
        "%vlocity_namespace%__DomainObjectCreationOrder__c": 1,
        "%vlocity_namespace%__DomainObjectFieldAPIName__c": "reasoncode",
        "%vlocity_namespace%__GlobalKey__c": "b6daf342-c03d-ba10-9091-ea76b94bbc14",
        "%vlocity_namespace%__IsDisabled__c": false,
        "%vlocity_namespace%__IsRequiredForUpsert__c": false,
        "%vlocity_namespace%__MapId__c": "INWIB2C-DRE-GetFRL_OSS_Migration_PrepCustom8115",
        "%vlocity_namespace%__OMplusSyncEnabled__c": true,
        "%vlocity_namespace%__UpsertKey__c": false,
        "CurrencyIsoCode": "MAD",
        "Name": "INWIB2C-DRE-GetFRL_OSS_Migration_Prep",
        "VlocityDataPackType": "SObject",
        "VlocityRecordSObjectType": "%vlocity_namespace%__DRMapItem__c"
    },
    {
        "%vlocity_namespace%__DefaultValue__c": "B2CPOST",
        "%vlocity_namespace%__DomainObjectAPIName__c": "json",
        "%vlocity_namespace%__DomainObjectCreationOrder__c": 1,
        "%vlocity_namespace%__DomainObjectFieldAPIName__c": "relatedParty:OLD_TYPE_LIGNE",
        "%vlocity_namespace%__GlobalKey__c": "e478ac0c-d357-2bd3-7386-d1dd8163f23b",
        "%vlocity_namespace%__IsDisabled__c": false,
        "%vlocity_namespace%__IsRequiredForUpsert__c": false,
        "%vlocity_namespace%__MapId__c": "INWIB2C-DRE-GetFRL_OSS_Migration_PrepCustom3206",
        "%vlocity_namespace%__OMplusSyncEnabled__c": true,
        "%vlocity_namespace%__UpsertKey__c": false,
        "CurrencyIsoCode": "MAD",
        "Name": "INWIB2C-DRE-GetFRL_OSS_Migration_Prep",
        "VlocityDataPackType": "SObject",
        "VlocityRecordSObjectType": "%vlocity_namespace%__DRMapItem__c"
    },
    {
        "%vlocity_namespace%__DefaultValue__c": "B2CPRE",
        "%vlocity_namespace%__DomainObjectAPIName__c": "json",
        "%vlocity_namespace%__DomainObjectCreationOrder__c": 1,
        "%vlocity_namespace%__DomainObjectFieldAPIName__c": "relatedParty:TYPE_LIGNE",
        "%vlocity_namespace%__GlobalKey__c": "b3a3e893-141f-4629-4329-90d5f13d8dcc",
        "%vlocity_namespace%__IsDisabled__c": false,
        "%vlocity_namespace%__IsRequiredForUpsert__c": false,
        "%vlocity_namespace%__MapId__c": "INWIB2C-DRE-GetFRL_OSS_Migration_PrepCustom139",
        "%vlocity_namespace%__OMplusSyncEnabled__c": true,
        "%vlocity_namespace%__UpsertKey__c": false,
        "CurrencyIsoCode": "MAD",
        "Name": "INWIB2C-DRE-GetFRL_OSS_Migration_Prep",
        "VlocityDataPackType": "SObject",
        "VlocityRecordSObjectType": "%vlocity_namespace%__DRMapItem__c"
    },
    {
        "%vlocity_namespace%__DomainObjectAPIName__c": "json",
        "%vlocity_namespace%__DomainObjectCreationOrder__c": 1,
        "%vlocity_namespace%__DomainObjectFieldAPIName__c": "resourceRef",
        "%vlocity_namespace%__DomainObjectFieldType__c": "List<Map>",
        "%vlocity_namespace%__GlobalKey__c": "3d0ad5bd-3236-b945-c506-30dde97d1d14",
        "%vlocity_namespace%__IsDisabled__c": false,
        "%vlocity_namespace%__IsRequiredForUpsert__c": false,
        "%vlocity_namespace%__MapId__c": "INWIB2C-DRE-GetFRL_OSS_Migration_PrepCustom6157",
        "%vlocity_namespace%__OMplusSyncEnabled__c": true,
        "%vlocity_namespace%__UpsertKey__c": false,
        "CurrencyIsoCode": "MAD",
        "Name": "INWIB2C-DRE-GetFRL_OSS_Migration_Prep",
        "VlocityDataPackType": "SObject",
        "VlocityRecordSObjectType": "%vlocity_namespace%__DRMapItem__c"
    },
    {
        "%vlocity_namespace%__DefaultValue__c": "SF",
        "%vlocity_namespace%__DomainObjectAPIName__c": "json",
        "%vlocity_namespace%__DomainObjectCreationOrder__c": 1,
        "%vlocity_namespace%__DomainObjectFieldAPIName__c": "resourceRef:DESTINATION",
        "%vlocity_namespace%__GlobalKey__c": "9b458910-1123-eb00-110f-c8e2229327b0",
        "%vlocity_namespace%__IsDisabled__c": false,
        "%vlocity_namespace%__IsRequiredForUpsert__c": false,
        "%vlocity_namespace%__MapId__c": "INWIB2C-DRE-GetFRL_OSS_Migration_PrepCustom1719",
        "%vlocity_namespace%__OMplusSyncEnabled__c": true,
        "%vlocity_namespace%__UpsertKey__c": false,
        "CurrencyIsoCode": "MAD",
        "Name": "INWIB2C-DRE-GetFRL_OSS_Migration_Prep",
        "VlocityDataPackType": "SObject",
        "VlocityRecordSObjectType": "%vlocity_namespace%__DRMapItem__c"
    },
    {
        "%vlocity_namespace%__DomainObjectAPIName__c": "json",
        "%vlocity_namespace%__DomainObjectCreationOrder__c": 1,
        "%vlocity_namespace%__DomainObjectFieldAPIName__c": "resourceRef:ICCID",
        "%vlocity_namespace%__GlobalKey__c": "008458b3-9e79-f08f-12eb-bd5705ed56aa",
        "%vlocity_namespace%__InterfaceFieldAPIName__c": "FRL:ChildFRL:@INWIB2C_ATT_DC_ICCID",
        "%vlocity_namespace%__IsDisabled__c": false,
        "%vlocity_namespace%__IsRequiredForUpsert__c": false,
        "%vlocity_namespace%__MapId__c": "INWIB2C-DRE-GetFRL_OSS_Migration_PrepCustom948",
        "%vlocity_namespace%__OMplusSyncEnabled__c": true,
        "%vlocity_namespace%__UpsertKey__c": false,
        "CurrencyIsoCode": "MAD",
        "Name": "INWIB2C-DRE-GetFRL_OSS_Migration_Prep",
        "VlocityDataPackType": "SObject",
        "VlocityRecordSObjectType": "%vlocity_namespace%__DRMapItem__c"
    },
    {
        "%vlocity_namespace%__DomainObjectAPIName__c": "json",
        "%vlocity_namespace%__DomainObjectCreationOrder__c": 1,
        "%vlocity_namespace%__DomainObjectFieldAPIName__c": "resourceRef:IMSI",
        "%vlocity_namespace%__GlobalKey__c": "19de9285-a79a-024a-ff1d-182b7836d7d5",
        "%vlocity_namespace%__InterfaceFieldAPIName__c": "FRL:ChildFRL:@INWIB2C_ATT_DC_IMSI",
        "%vlocity_namespace%__IsDisabled__c": false,
        "%vlocity_namespace%__IsRequiredForUpsert__c": false,
        "%vlocity_namespace%__MapId__c": "INWIB2C-DRE-GetFRL_OSS_Migration_PrepCustom6145",
        "%vlocity_namespace%__OMplusSyncEnabled__c": true,
        "%vlocity_namespace%__UpsertKey__c": false,
        "CurrencyIsoCode": "MAD",
        "Name": "INWIB2C-DRE-GetFRL_OSS_Migration_Prep",
        "VlocityDataPackType": "SObject",
        "VlocityRecordSObjectType": "%vlocity_namespace%__DRMapItem__c"
    },
    {
        "%vlocity_namespace%__DefaultValue__c": "84001",
        "%vlocity_namespace%__DomainObjectAPIName__c": "json",
        "%vlocity_namespace%__DomainObjectCreationOrder__c": 1,
        "%vlocity_namespace%__DomainObjectFieldAPIName__c": "resourceRef:INPROFILE",
        "%vlocity_namespace%__GlobalKey__c": "1b765d3f-9068-7267-a161-2d023ea55b64",
        "%vlocity_namespace%__IsDisabled__c": false,
        "%vlocity_namespace%__IsRequiredForUpsert__c": false,
        "%vlocity_namespace%__MapId__c": "INWIB2C-DRE-GetFRL_OSS_Migration_PrepCustom2039",
        "%vlocity_namespace%__OMplusSyncEnabled__c": true,
        "%vlocity_namespace%__UpsertKey__c": false,
        "CurrencyIsoCode": "MAD",
        "Name": "INWIB2C-DRE-GetFRL_OSS_Migration_Prep",
        "VlocityDataPackType": "SObject",
        "VlocityRecordSObjectType": "%vlocity_namespace%__DRMapItem__c"
    },
    {
        "%vlocity_namespace%__DefaultValue__c": "MOD",
        "%vlocity_namespace%__DomainObjectAPIName__c": "json",
        "%vlocity_namespace%__DomainObjectCreationOrder__c": 1,
        "%vlocity_namespace%__DomainObjectFieldAPIName__c": "resourceRef:INPROFILE_CHANGE",
        "%vlocity_namespace%__GlobalKey__c": "ee21fd22-0be9-0585-bf32-f226c1669999",
        "%vlocity_namespace%__IsDisabled__c": false,
        "%vlocity_namespace%__IsRequiredForUpsert__c": false,
        "%vlocity_namespace%__MapId__c": "INWIB2C-DRE-GetFRL_OSS_Migration_PrepCustom2302",
        "%vlocity_namespace%__OMplusSyncEnabled__c": true,
        "%vlocity_namespace%__UpsertKey__c": false,
        "CurrencyIsoCode": "MAD",
        "Name": "INWIB2C-DRE-GetFRL_OSS_Migration_Prep",
        "VlocityDataPackType": "SObject",
        "VlocityRecordSObjectType": "%vlocity_namespace%__DRMapItem__c"
    },
    {
        "%vlocity_namespace%__DomainObjectAPIName__c": "json",
        "%vlocity_namespace%__DomainObjectCreationOrder__c": 1,
        "%vlocity_namespace%__DomainObjectFieldAPIName__c": "resourceRef:KI",
        "%vlocity_namespace%__GlobalKey__c": "01f11ac4-38b4-9616-1eea-d2a586abe073",
        "%vlocity_namespace%__InterfaceFieldAPIName__c": "FRL:ChildFRL:@INWIB2C_ATT_DC_KI",
        "%vlocity_namespace%__IsDisabled__c": false,
        "%vlocity_namespace%__IsRequiredForUpsert__c": false,
        "%vlocity_namespace%__MapId__c": "INWIB2C-DRE-GetFRL_OSS_Migration_PrepCustom5915",
        "%vlocity_namespace%__OMplusSyncEnabled__c": true,
        "%vlocity_namespace%__UpsertKey__c": false,
        "CurrencyIsoCode": "MAD",
        "Name": "INWIB2C-DRE-GetFRL_OSS_Migration_Prep",
        "VlocityDataPackType": "SObject",
        "VlocityRecordSObjectType": "%vlocity_namespace%__DRMapItem__c"
    },
    {
        "%vlocity_namespace%__DomainObjectAPIName__c": "json",
        "%vlocity_namespace%__DomainObjectCreationOrder__c": 1,
        "%vlocity_namespace%__DomainObjectFieldAPIName__c": "resourceRef:MSISDN",
        "%vlocity_namespace%__GlobalKey__c": "7e3ca889-4caa-5a68-d7a5-56a214f656ae",
        "%vlocity_namespace%__InterfaceFieldAPIName__c": "FRL:ChildFRL:@INWIB2C_ATT_DC_MSISDN_FINAL",
        "%vlocity_namespace%__IsDisabled__c": false,
        "%vlocity_namespace%__IsRequiredForUpsert__c": false,
        "%vlocity_namespace%__MapId__c": "INWIB2C-DRE-GetFRL_OSS_Migration_PrepCustom9421",
        "%vlocity_namespace%__OMplusSyncEnabled__c": true,
        "%vlocity_namespace%__UpsertKey__c": false,
        "CurrencyIsoCode": "MAD",
        "Name": "INWIB2C-DRE-GetFRL_OSS_Migration_Prep",
        "VlocityDataPackType": "SObject",
        "VlocityRecordSObjectType": "%vlocity_namespace%__DRMapItem__c"
    },
    {
        "%vlocity_namespace%__DomainObjectAPIName__c": "json",
        "%vlocity_namespace%__DomainObjectCreationOrder__c": 1,
        "%vlocity_namespace%__DomainObjectFieldAPIName__c": "resourceRef:OCSID",
        "%vlocity_namespace%__GlobalKey__c": "e6da6450-17b9-fa8e-e9e3-86a30259bc10",
        "%vlocity_namespace%__InterfaceFieldAPIName__c": "FRL:ChildFRL:@INWIB2C_ATT_DC_OCSID",
        "%vlocity_namespace%__IsDisabled__c": false,
        "%vlocity_namespace%__IsRequiredForUpsert__c": false,
        "%vlocity_namespace%__MapId__c": "INWIB2C-DRE-GetFRL_OSS_Migration_PrepCustom2277",
        "%vlocity_namespace%__OMplusSyncEnabled__c": true,
        "%vlocity_namespace%__UpsertKey__c": false,
        "CurrencyIsoCode": "MAD",
        "Name": "INWIB2C-DRE-GetFRL_OSS_Migration_Prep",
        "VlocityDataPackType": "SObject",
        "VlocityRecordSObjectType": "%vlocity_namespace%__DRMapItem__c"
    },
    {
        "%vlocity_namespace%__DomainObjectAPIName__c": "json",
        "%vlocity_namespace%__DomainObjectCreationOrder__c": 1,
        "%vlocity_namespace%__DomainObjectFieldAPIName__c": "resourceRef:OFFER_TYPE",
        "%vlocity_namespace%__GlobalKey__c": "df7a57e9-2b7b-a8d4-f2a2-23534366fa16",
        "%vlocity_namespace%__IsDisabled__c": false,
        "%vlocity_namespace%__IsRequiredForUpsert__c": false,
        "%vlocity_namespace%__MapId__c": "INWIB2C-DRE-GetFRL_OSS_Migration_PrepCustom345",
        "%vlocity_namespace%__OMplusSyncEnabled__c": true,
        "%vlocity_namespace%__UpsertKey__c": false,
        "CurrencyIsoCode": "MAD",
        "Name": "INWIB2C-DRE-GetFRL_OSS_Migration_Prep",
        "VlocityDataPackType": "SObject",
        "VlocityRecordSObjectType": "%vlocity_namespace%__DRMapItem__c"
    },
    {
        "%vlocity_namespace%__DomainObjectAPIName__c": "json",
        "%vlocity_namespace%__DomainObjectCreationOrder__c": 1,
        "%vlocity_namespace%__DomainObjectFieldAPIName__c": "resourceRef:OLD_INPROFILE",
        "%vlocity_namespace%__GlobalKey__c": "2376a179-15d0-5b2b-88ac-fcaaf374f785",
        "%vlocity_namespace%__InterfaceFieldAPIName__c": "FRL:@INWIB2C_ATT_DC_PROFILIN",
        "%vlocity_namespace%__IsDisabled__c": false,
        "%vlocity_namespace%__IsRequiredForUpsert__c": false,
        "%vlocity_namespace%__MapId__c": "INWIB2C-DRE-GetFRL_OSS_Migration_PrepCustom9588",
        "%vlocity_namespace%__OMplusSyncEnabled__c": true,
        "%vlocity_namespace%__UpsertKey__c": false,
        "CurrencyIsoCode": "MAD",
        "Name": "INWIB2C-DRE-GetFRL_OSS_Migration_Prep",
        "VlocityDataPackType": "SObject",
        "VlocityRecordSObjectType": "%vlocity_namespace%__DRMapItem__c"
    },
    {
        "%vlocity_namespace%__DomainObjectAPIName__c": "json",
        "%vlocity_namespace%__DomainObjectCreationOrder__c": 1,
        "%vlocity_namespace%__DomainObjectFieldAPIName__c": "resourceRef:OLD_OCSID",
        "%vlocity_namespace%__GlobalKey__c": "529abaef-a2b5-b390-0a85-f57ea650903c",
        "%vlocity_namespace%__InterfaceFieldAPIName__c": "FRL:ChildFRL:@INWIB2C_ATT_DC_OldOCSId",
        "%vlocity_namespace%__IsDisabled__c": false,
        "%vlocity_namespace%__IsRequiredForUpsert__c": false,
        "%vlocity_namespace%__MapId__c": "INWIB2C-DRE-GetFRL_OSS_Migration_PrepCustom1392",
        "%vlocity_namespace%__OMplusSyncEnabled__c": true,
        "%vlocity_namespace%__UpsertKey__c": false,
        "CurrencyIsoCode": "MAD",
        "Name": "INWIB2C-DRE-GetFRL_OSS_Migration_Prep",
        "VlocityDataPackType": "SObject",
        "VlocityRecordSObjectType": "%vlocity_namespace%__DRMapItem__c"
    },
    {
        "%vlocity_namespace%__DefaultValue__c": "54",
        "%vlocity_namespace%__DomainObjectAPIName__c": "json",
        "%vlocity_namespace%__DomainObjectCreationOrder__c": 1,
        "%vlocity_namespace%__DomainObjectFieldAPIName__c": "resourceRef:PARAMETER_OCS",
        "%vlocity_namespace%__GlobalKey__c": "6a73c824-f773-b949-935c-08b6b206b50b",
        "%vlocity_namespace%__IsDisabled__c": false,
        "%vlocity_namespace%__IsRequiredForUpsert__c": false,
        "%vlocity_namespace%__MapId__c": "INWIB2C-DRE-GetFRL_OSS_Migration_PrepCustom7048",
        "%vlocity_namespace%__OMplusSyncEnabled__c": true,
        "%vlocity_namespace%__UpsertKey__c": false,
        "CurrencyIsoCode": "MAD",
        "Name": "INWIB2C-DRE-GetFRL_OSS_Migration_Prep",
        "VlocityDataPackType": "SObject",
        "VlocityRecordSObjectType": "%vlocity_namespace%__DRMapItem__c"
    },
    {
        "%vlocity_namespace%__DefaultValue__c": "9991122335",
        "%vlocity_namespace%__DomainObjectAPIName__c": "json",
        "%vlocity_namespace%__DomainObjectCreationOrder__c": 1,
        "%vlocity_namespace%__DomainObjectFieldAPIName__c": "resourceRef:VMS_PROFILE",
        "%vlocity_namespace%__GlobalKey__c": "1b7444cb-b3e4-c6ad-2b89-c8bee9419636",
        "%vlocity_namespace%__IsDisabled__c": false,
        "%vlocity_namespace%__IsRequiredForUpsert__c": false,
        "%vlocity_namespace%__MapId__c": "INWIB2C-DRE-GetFRL_OSS_Migration_PrepCustom5182",
        "%vlocity_namespace%__OMplusSyncEnabled__c": true,
        "%vlocity_namespace%__UpsertKey__c": false,
        "CurrencyIsoCode": "MAD",
        "Name": "INWIB2C-DRE-GetFRL_OSS_Migration_Prep",
        "VlocityDataPackType": "SObject",
        "VlocityRecordSObjectType": "%vlocity_namespace%__DRMapItem__c"
    },
    {
        "%vlocity_namespace%__DomainObjectAPIName__c": "json",
        "%vlocity_namespace%__DomainObjectCreationOrder__c": 1,
        "%vlocity_namespace%__DomainObjectFieldAPIName__c": "serviceOrderItem:action",
        "%vlocity_namespace%__GlobalKey__c": "23897e32-d03e-c386-f315-f157c662a12a",
        "%vlocity_namespace%__InterfaceFieldAPIName__c": "FRL:ChildFRL:ACTION",
        "%vlocity_namespace%__IsDisabled__c": false,
        "%vlocity_namespace%__IsRequiredForUpsert__c": false,
        "%vlocity_namespace%__MapId__c": "INWIB2C-DRE-GetFRL_OSS_Migration_PrepCustom7366",
        "%vlocity_namespace%__OMplusSyncEnabled__c": true,
        "%vlocity_namespace%__UpsertKey__c": false,
        "CurrencyIsoCode": "MAD",
        "Name": "INWIB2C-DRE-GetFRL_OSS_Migration_Prep",
        "VlocityDataPackType": "SObject",
        "VlocityRecordSObjectType": "%vlocity_namespace%__DRMapItem__c"
    },
    {
        "%vlocity_namespace%__DomainObjectAPIName__c": "json",
        "%vlocity_namespace%__DomainObjectCreationOrder__c": 1,
        "%vlocity_namespace%__DomainObjectFieldAPIName__c": "serviceOrderItem:code",
        "%vlocity_namespace%__GlobalKey__c": "dc79c371-1344-6b95-f3e9-f574a68512fa",
        "%vlocity_namespace%__InterfaceFieldAPIName__c": "FRL:ChildFRL:@INWIB2C_ATT_DC_OSS_SERVICE_CODE",
        "%vlocity_namespace%__IsDisabled__c": false,
        "%vlocity_namespace%__IsRequiredForUpsert__c": false,
        "%vlocity_namespace%__MapId__c": "INWIB2C-DRE-GetFRL_OSS_Migration_PrepCustom5808",
        "%vlocity_namespace%__OMplusSyncEnabled__c": true,
        "%vlocity_namespace%__UpsertKey__c": false,
        "CurrencyIsoCode": "MAD",
        "Name": "INWIB2C-DRE-GetFRL_OSS_Migration_Prep",
        "VlocityDataPackType": "SObject",
        "VlocityRecordSObjectType": "%vlocity_namespace%__DRMapItem__c"
    },
    {
        "%vlocity_namespace%__DomainObjectAPIName__c": "json",
        "%vlocity_namespace%__DomainObjectCreationOrder__c": 1,
        "%vlocity_namespace%__DomainObjectFieldAPIName__c": "serviceOrderItem:serviceRefOrValue:characteristic:CALL_TRANSFER_LEVEL:code",
        "%vlocity_namespace%__GlobalKey__c": "580138f3-2971-e28c-2690-8b5b86ab2d23",
        "%vlocity_namespace%__InterfaceFieldAPIName__c": "FRL:ChildFRL:CALL_TRANSFER_LEVEL_Code",
        "%vlocity_namespace%__IsDisabled__c": false,
        "%vlocity_namespace%__IsRequiredForUpsert__c": false,
        "%vlocity_namespace%__MapId__c": "INWIB2C-DRE-GetFRL_OSS_Migration_PrepCustom6890",
        "%vlocity_namespace%__OMplusSyncEnabled__c": true,
        "%vlocity_namespace%__UpsertKey__c": false,
        "CurrencyIsoCode": "MAD",
        "Name": "INWIB2C-DRE-GetFRL_OSS_Migration_Prep",
        "VlocityDataPackType": "SObject",
        "VlocityRecordSObjectType": "%vlocity_namespace%__DRMapItem__c"
    },
    {
        "%vlocity_namespace%__DomainObjectAPIName__c": "json",
        "%vlocity_namespace%__DomainObjectCreationOrder__c": 1,
        "%vlocity_namespace%__DomainObjectFieldAPIName__c": "serviceOrderItem:serviceRefOrValue:characteristic:IROAM_SERVICE_LEVEL:code",
        "%vlocity_namespace%__GlobalKey__c": "af5fb2f0-c1cb-990d-97a7-1b1b5b130614",
        "%vlocity_namespace%__InterfaceFieldAPIName__c": "FRL:ChildFRL:IROAM_SERVICE_LEVEL_Code",
        "%vlocity_namespace%__IsDisabled__c": false,
        "%vlocity_namespace%__IsRequiredForUpsert__c": false,
        "%vlocity_namespace%__MapId__c": "INWIB2C-DRE-GetFRL_OSS_Migration_PrepCustom2700",
        "%vlocity_namespace%__OMplusSyncEnabled__c": true,
        "%vlocity_namespace%__UpsertKey__c": false,
        "CurrencyIsoCode": "MAD",
        "Name": "INWIB2C-DRE-GetFRL_OSS_Migration_Prep",
        "VlocityDataPackType": "SObject",
        "VlocityRecordSObjectType": "%vlocity_namespace%__DRMapItem__c"
    },
    {
        "%vlocity_namespace%__DomainObjectAPIName__c": "json",
        "%vlocity_namespace%__DomainObjectCreationOrder__c": 1,
        "%vlocity_namespace%__DomainObjectFieldAPIName__c": "serviceOrderItem:serviceRefOrValue:characteristic:SERVICE_LEVEL_IN:code",
        "%vlocity_namespace%__GlobalKey__c": "e18cd918-5dfe-f5e0-a78e-300c8fcdc3db",
        "%vlocity_namespace%__InterfaceFieldAPIName__c": "FRL:ChildFRL:SERVICE_LEVEL_IN_Code",
        "%vlocity_namespace%__IsDisabled__c": false,
        "%vlocity_namespace%__IsRequiredForUpsert__c": false,
        "%vlocity_namespace%__MapId__c": "INWIB2C-DRE-GetFRL_OSS_Migration_PrepCustom8987",
        "%vlocity_namespace%__OMplusSyncEnabled__c": true,
        "%vlocity_namespace%__UpsertKey__c": false,
        "CurrencyIsoCode": "MAD",
        "Name": "INWIB2C-DRE-GetFRL_OSS_Migration_Prep",
        "VlocityDataPackType": "SObject",
        "VlocityRecordSObjectType": "%vlocity_namespace%__DRMapItem__c"
    },
    {
        "%vlocity_namespace%__DomainObjectAPIName__c": "json",
        "%vlocity_namespace%__DomainObjectCreationOrder__c": 1,
        "%vlocity_namespace%__DomainObjectFieldAPIName__c": "serviceOrderItem:serviceRefOrValue:characteristic:SERVICE_LEVEL_IN:value",
        "%vlocity_namespace%__GlobalKey__c": "40fe72e7-eb5a-926d-7942-0c2c341dc8b1",
        "%vlocity_namespace%__InterfaceFieldAPIName__c": "FRL:ChildFRL:SERVICE_LEVEL_IN_Value",
        "%vlocity_namespace%__IsDisabled__c": false,
        "%vlocity_namespace%__IsRequiredForUpsert__c": false,
        "%vlocity_namespace%__MapId__c": "INWIB2C-DRE-GetFRL_OSS_Migration_PrepCustom5115",
        "%vlocity_namespace%__OMplusSyncEnabled__c": true,
        "%vlocity_namespace%__UpsertKey__c": false,
        "CurrencyIsoCode": "MAD",
        "Name": "INWIB2C-DRE-GetFRL_OSS_Migration_Prep",
        "VlocityDataPackType": "SObject",
        "VlocityRecordSObjectType": "%vlocity_namespace%__DRMapItem__c"
    },
    {
        "%vlocity_namespace%__DomainObjectAPIName__c": "json",
        "%vlocity_namespace%__DomainObjectCreationOrder__c": 1,
        "%vlocity_namespace%__DomainObjectFieldAPIName__c": "serviceOrderItem:serviceRefOrValue:characteristic:SERVICE_LEVEL_OUT:code",
        "%vlocity_namespace%__GlobalKey__c": "96213376-9249-f5ce-f304-650519fcb868",
        "%vlocity_namespace%__InterfaceFieldAPIName__c": "FRL:ChildFRL:SERVICE_LEVEL_OUT_Code",
        "%vlocity_namespace%__IsDisabled__c": false,
        "%vlocity_namespace%__IsRequiredForUpsert__c": false,
        "%vlocity_namespace%__MapId__c": "INWIB2C-DRE-GetFRL_OSS_Migration_PrepCustom2795",
        "%vlocity_namespace%__OMplusSyncEnabled__c": true,
        "%vlocity_namespace%__UpsertKey__c": false,
        "CurrencyIsoCode": "MAD",
        "Name": "INWIB2C-DRE-GetFRL_OSS_Migration_Prep",
        "VlocityDataPackType": "SObject",
        "VlocityRecordSObjectType": "%vlocity_namespace%__DRMapItem__c"
    },
    {
        "%vlocity_namespace%__DomainObjectAPIName__c": "json",
        "%vlocity_namespace%__DomainObjectCreationOrder__c": 1,
        "%vlocity_namespace%__DomainObjectFieldAPIName__c": "serviceOrderItem:serviceRefOrValue:characteristic:SERVICE_STATUS:code",
        "%vlocity_namespace%__GlobalKey__c": "3be643c5-a932-0ba8-72d8-d5ad5113f136",
        "%vlocity_namespace%__InterfaceFieldAPIName__c": "FRL:ChildFRL:SERVICE_STATUS_Code",
        "%vlocity_namespace%__IsDisabled__c": false,
        "%vlocity_namespace%__IsRequiredForUpsert__c": false,
        "%vlocity_namespace%__MapId__c": "INWIB2C-DRE-GetFRL_OSS_Migration_PrepCustom6917",
        "%vlocity_namespace%__OMplusSyncEnabled__c": true,
        "%vlocity_namespace%__UpsertKey__c": false,
        "CurrencyIsoCode": "MAD",
        "Name": "INWIB2C-DRE-GetFRL_OSS_Migration_Prep",
        "VlocityDataPackType": "SObject",
        "VlocityRecordSObjectType": "%vlocity_namespace%__DRMapItem__c"
    },
    {
        "%vlocity_namespace%__DomainObjectAPIName__c": "json",
        "%vlocity_namespace%__DomainObjectCreationOrder__c": 1,
        "%vlocity_namespace%__DomainObjectFieldAPIName__c": "serviceOrderItem:serviceRefOrValue:characteristic:SMS_IN:code",
        "%vlocity_namespace%__GlobalKey__c": "641b7da3-2966-df17-c8b9-af9ccf3a3ffa",
        "%vlocity_namespace%__InterfaceFieldAPIName__c": "FRL:ChildFRL:SMS_IN_Code",
        "%vlocity_namespace%__IsDisabled__c": false,
        "%vlocity_namespace%__IsRequiredForUpsert__c": false,
        "%vlocity_namespace%__MapId__c": "INWIB2C-DRE-GetFRL_OSS_Migration_PrepCustom753",
        "%vlocity_namespace%__OMplusSyncEnabled__c": true,
        "%vlocity_namespace%__UpsertKey__c": false,
        "CurrencyIsoCode": "MAD",
        "Name": "INWIB2C-DRE-GetFRL_OSS_Migration_Prep",
        "VlocityDataPackType": "SObject",
        "VlocityRecordSObjectType": "%vlocity_namespace%__DRMapItem__c"
    },
    {
        "%vlocity_namespace%__DomainObjectAPIName__c": "json",
        "%vlocity_namespace%__DomainObjectCreationOrder__c": 1,
        "%vlocity_namespace%__DomainObjectFieldAPIName__c": "serviceOrderItem:serviceRefOrValue:characteristic:SMS_OUT:code",
        "%vlocity_namespace%__GlobalKey__c": "a69aa86e-33be-97cd-df82-74a181c864f7",
        "%vlocity_namespace%__InterfaceFieldAPIName__c": "FRL:ChildFRL:SMS_OUT_Code",
        "%vlocity_namespace%__IsDisabled__c": false,
        "%vlocity_namespace%__IsRequiredForUpsert__c": false,
        "%vlocity_namespace%__MapId__c": "INWIB2C-DRE-GetFRL_OSS_Migration_PrepCustom1098",
        "%vlocity_namespace%__OMplusSyncEnabled__c": true,
        "%vlocity_namespace%__UpsertKey__c": false,
        "CurrencyIsoCode": "MAD",
        "Name": "INWIB2C-DRE-GetFRL_OSS_Migration_Prep",
        "VlocityDataPackType": "SObject",
        "VlocityRecordSObjectType": "%vlocity_namespace%__DRMapItem__c"
    }
]